hatchway/__init__.py
hatchway/apps.py
hatchway/constants.py
hatchway/http.py
hatchway/schema.py
hatchway/types.py
hatchway/urls.py
hatchway/view.py
django_hatchway-0.5.2.dist-info/LICENSE
django_hatchway-0.5.2.dist-info/METADATA
django_hatchway-0.5.2.dist-info/WHEEL
django_hatchway-0.5.2.dist-info/top_level.txt
django_hatchway-0.5.2.dist-info/RECORD
