Metadata-Version: 2.1
Name: django-hatchway
Version: 0.5.2
Summary: An unsurprising Django API framework
Author-email: Andrew Godwin <andrew@aeracode.org>
License: BSD-3-Clause
Classifier: Framework :: Django
Classifier: Programming Language :: Python :: 3
Requires-Python: >=3.10
License-File: LICENSE
Requires-Dist: django (>=4.0)
Requires-Dist: pydantic (~=1.10)
Provides-Extra: dev
Requires-Dist: pytest (~=7.2) ; extra == 'dev'
Requires-Dist: pytest-django (~=4.5) ; extra == 'dev'
